random_utils/__init__.py
random_utils/colors/__init__.py
random_utils/colors/conversions.py
random_utils/datatypes/__init__.py
random_utils/datatypes/queue.py
random_utils/datatypes/stack.py
random_utils/funcs/__init__.py
random_utils/math/__init__.py
random_utils/math/vector.py
random_utils/pygame/__init__.py
random_utils/time/__init__.py
random_utils-1.0.0.dist-info/LICENSE
random_utils-1.0.0.dist-info/METADATA
random_utils-1.0.0.dist-info/WHEEL
random_utils-1.0.0.dist-info/top_level.txt
random_utils-1.0.0.dist-info/RECORD
