Metadata-Version: 2.1
Name: random-utils
Version: 1.0.0
Summary: Module with various useful utilities.
Home-page: https://github.com/ArjunSahlot/random_utils
Author: Arjun Sahlot
Author-email: iarjun.sahlot@gmail.com
Classifier: Programming Language :: Python :: 3
Classifier: License :: OSI Approved :: GNU General Public License v2 or later (GPLv2+)
Classifier: Operating System :: OS Independent
License-File: LICENSE
Requires-Dist: numpy
